pypetting/__init__.py
pypetting/base.py
pypetting/errors.py
pypetting/infinite.py
pypetting/labware.py
pypetting/liha.py
pypetting/mca.py
pypetting/message.py
pypetting/misc.py
pypetting/roma.py
pypetting/storex.py
pypetting/teshake.py
pypetting/utils.py
pypetting/write.py
pypetting-1.0.0.dist-info/LICENSE.md
pypetting-1.0.0.dist-info/METADATA
pypetting-1.0.0.dist-info/WHEEL
pypetting-1.0.0.dist-info/entry_points.txt
pypetting-1.0.0.dist-info/top_level.txt
pypetting-1.0.0.dist-info/RECORD
