Metadata-Version: 2.1
Name: pypetting
Version: 1.0.0
Summary: Generate worklists for Tecan EVOware pipetting software
Home-page: https://github.com/sirno/pypetting
License: MIT
Platform: UNKNOWN
License-File: LICENSE.md
Requires-Dist: numpy
Requires-Dist: dataclasses-json
Requires-Dist: requests
Provides-Extra: dev
Requires-Dist: pylint ; extra == 'dev'
Requires-Dist: pytest ; extra == 'dev'
Requires-Dist: pytest-cov ; extra == 'dev'
